betacal/__init__.py
betacal/beta_calibration.py
betacal/version.py
betacal-1.1.0.dist-info/LICENSE.md
betacal-1.1.0.dist-info/METADATA
betacal-1.1.0.dist-info/WHEEL
betacal-1.1.0.dist-info/top_level.txt
betacal-1.1.0.dist-info/RECORD
