Metadata-Version: 2.1
Name: betacal
Version: 1.1.0
Summary: Beta calibration
Home-page: https://betacal.github.io/
Author: Telmo de Menezes e Silva Filho and Miquel Perello Nieto
Author-email: tmfilho@gmail.com
License: MIT
Download-URL: https://github.com/betacal/python/archive/refs/tags/1.1.0.tar.gz
Keywords: classifier calibration,calibration,classification
Platform: UNKNOWN
